LICENSE
MANIFEST.in
README.md
setup.py
atomos/__about__.py
atomos/__init__.py
atomos/atom.py
atomos/atomic.py
atomos/util.py
atomos.egg-info/PKG-INFO
atomos.egg-info/SOURCES.txt
atomos.egg-info/dependency_links.txt
atomos.egg-info/not-zip-safe
atomos.egg-info/requires.txt
atomos.egg-info/top_level.txt
atomos.egg-info/version_info.json
atomos/multiprocessing/__init__.py
atomos/multiprocessing/atom.py
atomos/multiprocessing/atomic.py