Metadata-Version: 1.1
Name: atomos
Version: 0.3.1
Summary: Atomic primitives for Python.
Home-page: https://github.com/maxcountryman/atomos
Author: Max Countryman
Author-email: Max Countryman
License: BSD
Keywords: atom atomic concurrency lock
Platform: UNKNOWN
Classifier: Development Status :: 5 - Production/Stable
Classifier: Intended Audience :: Developers
Classifier: Programming Language :: Python
Classifier: Programming Language :: Python :: 2
Classifier: Programming Language :: Python :: 2.7
Classifier: Programming Language :: Python :: 3
Classifier: Programming Language :: Python :: 3.3
Classifier: Programming Language :: Python :: 3.4
Classifier: Topic :: Utilities
Classifier: License :: OSI Approved :: BSD License
